pDSuAX/__init__.py
pDSuAX/add.py
pdsuax-0.0.1.dist-info/LICENSE
pdsuax-0.0.1.dist-info/WHEEL
pdsuax-0.0.1.dist-info/METADATA
pdsuax-0.0.1.dist-info/RECORD
