Metadata-Version: 2.1
Name: pDSuAX
Version: 0.0.1
Summary: Backported and Experimental Type Hints for Python 3.8+
Keywords: annotations,backport,checker,checking,function,hinting,hints,type,typechecking,typehinting,typehints,typing
Author-email: "Guido van Rossum, Jukka Lehtosalo, Łukasz Langa, Michael Lee" <levkivskyi@gmail.com>
Requires-Python: >=3.8
Classifier: Development Status :: 5 - Production/Stable
Classifier: Environment :: Console
Classifier: Intended Audience :: Developers
Classifier: License :: OSI Approved :: Python Software Foundation License
Classifier: Operating System :: OS Independent
Classifier: Programming Language :: Python :: 3
Classifier: Programming Language :: Python :: 3 :: Only
Classifier: Programming Language :: Python :: 3.8
Classifier: Programming Language :: Python :: 3.9
Classifier: Programming Language :: Python :: 3.10
Classifier: Programming Language :: Python :: 3.11
Classifier: Programming Language :: Python :: 3.12
Classifier: Programming Language :: Python :: 3.13
Classifier: Topic :: Software Development
Project-URL: Bug Tracker, https://github.com/python/typing_extensions/issues
Project-URL: Changes, https://github.com/python/typing_extensions/blob/main/CHANGELOG.md
Project-URL: Documentation, https://typing-extensions.readthedocs.io/
Project-URL: Home, https://github.com/python/typing_extensions
Project-URL: Q & A, https://github.com/python/typing/discussions
Project-URL: Repository, https://github.com/python/typing_extensions
